{"cameraMode":{"drawMode":0,"name":"Shaded","section":"Shading Mode"},"sceneLighting":true,"audioPlay":false,"sceneViewState":{"m_AlwaysRefresh":false,"showFog":true,"showSkybox":true,"showFlares":true,"showImageEffects":true,"showParticleSystems":true,"showVisualEffectGraphs":true,"m_FxEnabled":true},"in2DMode":false,"pivot":{"x":15.16698932647705,"y":9.293498992919922,"z":-24.77374267578125},"rotation":{"x":-0.0059350659139454369,"y":0.9926924109458923,"z":-0.054861485958099368,"w":-0.107341468334198},"size":5.572425842285156,"orthographic":false}